instalocker/ValAgents.py
instalocker/__init__.py
instalocker/instalocker.py
instalocker/images/1.ico
instalocker-1.0.0.dist-info/METADATA
instalocker-1.0.0.dist-info/WHEEL
instalocker-1.0.0.dist-info/entry_points.txt
instalocker-1.0.0.dist-info/top_level.txt
instalocker-1.0.0.dist-info/RECORD
